amgd/__init__.py
amgd/_init_.py
amgd/.ipynb_checkpoints/__init__-checkpoint.py
amgd/benchmarks/__init__.py
amgd/benchmarks/comparison.py
amgd/benchmarks/datasets.py
amgd/benchmarks/.ipynb_checkpoints/__init__-checkpoint.py
amgd/benchmarks/.ipynb_checkpoints/comparison-checkpoint.py
amgd/benchmarks/.ipynb_checkpoints/datasets-checkpoint.py
amgd/core/__init__.py
amgd/core/convergence.py
amgd/core/optimizer.py
amgd/core/penalties.py
amgd/core/.ipynb_checkpoints/__init__-checkpoint.py
amgd/core/.ipynb_checkpoints/convergence-checkpoint.py
amgd/core/.ipynb_checkpoints/optimizer-checkpoint.py
amgd/core/.ipynb_checkpoints/penalties-checkpoint.py
amgd/models/__init__.py
amgd/models/base.py
amgd/models/glm.py
amgd/models/poisson.py
amgd/models/.ipynb_checkpoints/__init__-checkpoint.py
amgd/models/.ipynb_checkpoints/base-checkpoint.py
amgd/models/.ipynb_checkpoints/glm-checkpoint.py
amgd/models/.ipynb_checkpoints/poisson-checkpoint.py
amgd/utils/__init__.py
amgd/utils/metrics.py
amgd/utils/preprocessing.py
amgd/utils/validation.py
amgd/utils/.ipynb_checkpoints/__init__-checkpoint.py
amgd/utils/.ipynb_checkpoints/metrics-checkpoint.py
amgd/utils/.ipynb_checkpoints/preprocessing-checkpoint.py
amgd/visualization/__init__.py
amgd/visualization/coefficients.py
amgd/visualization/convergence.py
amgd/visualization/.ipynb_checkpoints/coefficients-checkpoint.py
amgd/visualization/.ipynb_checkpoints/convergence-checkpoint.py
amgd-1.4.8.dist-info/licenses/LICENSE
amgd-1.4.8.dist-info/METADATA
amgd-1.4.8.dist-info/WHEEL
amgd-1.4.8.dist-info/top_level.txt
amgd-1.4.8.dist-info/RECORD
