Metadata-Version: 2.4
Name: amgd
Version: 1.4.8
Summary: Adaptive Momentum Gradient Descent for Regularized Poisson Regression
Home-page: https://github.com/elbakari01/amgd_package
Author: Ibrahim Bakari
Author-email: 2020913072@ogr.cu.edu.tr
License: MIT
Project-URL: Homepage, https://github.com/elbakari01/amgd_package
Project-URL: Repository, https://github.com/elbakari01/amgd_package
Project-URL: Bug Reports, https://github.com/elbakari01/amgd_package/issues
Project-URL: Documentation, https://amgd.readthedocs.io
Keywords: machine learning,poisson regression,optimization,sparsity,regularization
Classifier: Development Status :: 4 - Beta
Classifier: Intended Audience :: Science/Research
Classifier: License :: OSI Approved :: MIT License
Classifier: Programming Language :: Python :: 3
Classifier: Programming Language :: Python :: 3.8
Classifier: Programming Language :: Python :: 3.9
Classifier: Programming Language :: Python :: 3.10
Classifier: Programming Language :: Python :: 3.11
Classifier: Topic :: Scientific/Engineering :: Artificial Intelligence
Requires-Python: >=3.6
Requires-Dist: numpy>=1.20.0
Requires-Dist: scipy>=1.7.0
Requires-Dist: scikit-learn>=1.0.0
Requires-Dist: matplotlib>=3.3.0
Requires-Dist: pandas>=1.3.0
Dynamic: author
Dynamic: author-email
Dynamic: classifier
Dynamic: description
Dynamic: description-content-type
Dynamic: home-page
Dynamic: keywords
Dynamic: license
Dynamic: project-url
Dynamic: requires-dist
Dynamic: requires-python
Dynamic: summary
